[
    {
      "id": 1,
      "brand": "Rolex",
      "model": "Submariner",
      "price": 10000,
      "movement": "Automatic"
    },
    {
      "id": 2,
      "brand": "Omega",
      "model": "Speedmaster Professional",
      "price": 5000,
      "movement": "Manual"
    },
    {
      "id": 3,
      "brand": "Patek Philippe",
      "model": "Nautilus",
      "price": 30000,
      "movement": "Automatic"
    },
    {
      "id": 4,
      "brand": "Tag Heuer",
      "model": "Carrera",
      "price": 6000,
      "movement": "Automatic"
    },
    {
      "id": 5,
      "brand": "Audemars Piguet",
      "model": "Royal Oak",
      "price": 40000,
      "movement": "Automatic"
    },
    {
      "id": 6,
      "brand": "Seiko",
      "model": "Presage",
      "price": 500,
      "movement": "Automatic"
    },
    {
      "id": 7,
      "brand": "Casio",
      "model": "G-Shock",
      "price": 100,
      "movement": "Quartz"
    },
    {
      "id": 8,
      "brand": "Tissot",
      "model": "Le Locle",
      "price": 700,
      "movement": "Automatic"
    },
    {
      "id": 9,
      "brand": "Longines",
      "model": "Master Collection",
      "price": 1500,
      "movement": "Automatic"
    },
    {
      "id": 10,
      "brand": "Citizen",
      "model": "Eco-Drive",
      "price": 300,
      "movement": "Eco-Drive"
    }
  ]
  